Metadata-Version: 2.1
Name: large-language-model-cli
Version: 0.7
Summary: Command-line for interacting with large language models. not TUI. chatgpt
Home-page: https://github.com/talwrii/llmcli
Author: Talwrii
Author-email: Talwrii@googlemail.com
License: mit
Keywords: ChatGPT
Platform: UNKNOWN
